fireprompt/__init__.py
fireprompt/api.py
fireprompt/func.py
fireprompt/logger.py
fireprompt/prompt.py
fireprompt/promptasync.py
fireprompt/types.py
fireprompt-0.1.9.dist-info/licenses/LICENSE
fireprompt-0.1.9.dist-info/METADATA
fireprompt-0.1.9.dist-info/WHEEL
fireprompt-0.1.9.dist-info/top_level.txt
fireprompt-0.1.9.dist-info/RECORD
