Metadata-Version: 2.4
Name: fireprompt
Version: 0.1.9
Summary: Turn Python functions into LLM prompts
License: MIT
Requires-Python: >=3.10
License-File: LICENSE
Requires-Dist: litellm>=1.80.5
Requires-Dist: pydantic>=2.12.0
Requires-Dist: jinja2>=3.1.0
Requires-Dist: pyyaml>=6.0.0
Dynamic: license-file
